{
  "last_updated": 1685636234.0,
  "activity": [
    {
      "type": "comment_created",
      "title": "coronasafe/care_fe#3358",
      "time": 1685636234.0,
      "link": "https://github.com/coronasafe/care_fe/issues/3358#issuecomment-1572350866",
      "text": "Hi @skks1212 can I take up this issue if it is not yet resolved?"
    },
    {
      "type": "comment_created",
      "title": "coronasafe/care_fe#5524",
      "time": 1685017575.0,
      "link": "https://github.com/coronasafe/care_fe/issues/5524#issuecomment-1562818549",
      "text": "sure @rithviknishad "
    },
    {
      "type": "comment_created",
      "title": "coronasafe/care_fe#5524",
      "time": 1685016403.0,
      "link": "https://github.com/coronasafe/care_fe/issues/5524#issuecomment-1562789174",
      "text": "HI I have reproduced the behaviour at my end, let me know if I can work on it @rithviknishad "
    }
  ],
  "open_prs": [],
  "authored_issue_and_pr": []
}