{
  "last_updated": 1692619732.0,
  "activity": [
    {
      "type": "comment_created",
      "title": "coronasafe/care_fe#6061",
      "time": 1692619732.0,
      "link": "https://github.com/coronasafe/care_fe/issues/6061#issuecomment-1686209168",
      "text": "okay sure, thanks."
    },
    {
      "type": "comment_created",
      "title": "coronasafe/care_fe#6061",
      "time": 1692246665.0,
      "link": "https://github.com/coronasafe/care_fe/issues/6061#issuecomment-1681596066",
      "text": "thanks for assigning but I'm sorry about this, there seems to be a problem with subscribing to notifications action as I'm unable to get that on my device."
    },
    {
      "type": "comment_created",
      "title": "coronasafe/care_fe#6061",
      "time": 1692243642.0,
      "link": "https://github.com/coronasafe/care_fe/issues/6061#issuecomment-1681564066",
      "text": "hi,\r\nis this open? if it is I'd like to contribute.\r\nthank you in advance."
    }
  ],
  "open_prs": [],
  "authored_issue_and_pr": []
}